{
  "clients": {
    "Cristina Orlandea": {
      "paid": ["10.6", "12.6", "5.7", "8.7", "19.8", "21.8", "23.8", "13.9", "20.9", "23.9", "25.9", "9.10", "3.2", "7.2", "10.2", "12.2", "14.2", "31.3", "1.4", "14.4", "16.4", "9.4", "30.4", "1.5", "5.5"],
      "unpaid": [],
      "stats": {
        "total": 25,
        "paid": 25,
        "unpaid": 0,
        "remaining": 5
      }
    },
    "Alexandra Boboc": {
      "paid": ["10.6", "14.6", "17.6", "26.7", "2.8", "5.8", "9.8", "12.8", "19.8", "23.8", "13.9", "2.10", "7.10", "21.10", "25.10", "4.11", "8.11", "18.11", "25.11", "12.12.2024", "13.1", "17.1", "20.1"],
      "unpaid": ["21.3"],
      "stats": {
        "total": 24,
        "paid": 23,
        "unpaid": 1,
        "remaining": 6
      }
    },
    "Alexandra Bumbas": {
      "paid": ["26.6", "28.6", "1.7", "5.7", "8.7", "15.7", "17.9", "22.7", "2.8", "5.8", "7.8", "12.8", "21.8", "4.9", "6.9", "9.9", "11.9", "25.9", "27.9", "30.9", "4.10", "7.10", "14.10", "16.10", "21.10", "25.10", "30.10", "11.11", "18.11", "20.11", "22.11", "27.11", "2.12.2024", "4.12", "6.12", "9.12", "11.12", "13.12", "16.12", "6.1", "8.1", "10.1", "13.1", "15.1", "17.1", "20.1", "22.1", "27.1", "27.1", "29.1", "3.2", "5.2", "11.2", "10.2", "12.2", "14.2", "17.2", "3.3", "5.3", "7.3", "10.3", "12.3", "14.3", "17.3", "24.3", "26.3", "28.3", "31.3", "2.4", "4.4", "7.4", "9.4", "18.4", "28.4", "30.4", "5.5", "7.5", "9.5", "12.5", "19.5", "26.5", "28.5", "2.6", "4.6", "11.6", "16.6", "12.6"],
      "unpaid": [],
      "stats": {
        "total": 85,
        "paid": 85,
        "unpaid": 0,
        "remaining": 5
      }
    }
  },
  "updated": "2025-06-18"
}